Workbook

Sheet ReadMe
A1: Raymond Priestley Centre — Centre Manager Workbook
A3: HOW THIS WORKBOOK WORKS
A4: One workbook, five working sheets. Enter data in Bookings, StaffExtras and Costs;
A5: the Dashboard summarises everything by financial year (1 Aug - 31 Jul).
A7: COLOUR LEGEND
A8: Cream cells = type your data here (inputs)
A9: White cells = formulas - do not overwrite
A10: Yellow fill = the Dashboard year selector
A12: SHEET GUIDE
A13: Bookings - one row per booking/course. Type: name, product, client, dates, people,
A14: Discount, Deposit and Received. Agreed £ fills in automatically from the price bands
A15: (overtype it with the actual invoiced amount whenever one is agreed).
... A37: Prepared by the University of Birmingham MSc Business Analytics capstone team, 2026.

Sheet Reference
A1: Reference data — edit prices/rates here; lookups update everywhere
A3: PRICE BANDS (per night)
A4: Product | B4: Client | C4: Tier (people) | D4: Key | E4: Rate £ | F4: Basis | H4: Products | I4: Clients
A5: Homeport | B5: UoB | C5: 32 | D5: =A5&"|"&B5&"|"&C5 -> Homeport|UoB|32 | E5: 3350 | F5: per night | H5: Homeport | I5: UoB
A6: Homeport | B6: UoB | C6: 40 | D6: =A6&"|"&B6&"|"&C6 -> Homeport|UoB|40 | E6: 4150 | F6: per night | H6: Sherpa | I6: External
A7: Homeport | B7: External | C7: 32 | D7: =A7&"|"&B7&"|"&C7 -> Homeport|External|32 | E7: 3800 | F7: per night | H7: Recreation | I7: Mixed
A8: Homeport | B8: External | C8: 40 | D8: =A8&"|"&B8&"|"&C8 -> Homeport|External|40 | E8: 4700 | F8: per night | H8: Others | I8: Unknown
A9: Sherpa | B9: UoB | C9: 32 | D9: =A9&"|"&B9&"|"&C9 -> Sherpa|UoB|32 | E9: 2250 | F9: per night
A10: Sherpa | B10: UoB | C10: 40 | D10: =A10&"|"&B10&"|"&C10 -> Sherpa|UoB|40 | E10: 2650 | F10: per night
A11: Sherpa | B11: External | C11: 32 | D11: =A11&"|"&B11&"|"&C11 -> Sherpa|External|32 | E11: 2630 | F11: per night
A12: Sherpa | B12: External | C12: 40 | D12: =A12&"|"&B12&"|"&C12 -> Sherpa|External|40 | E12: 3025 | F12: per night
A13: Homeport/Sherpa are per night. Recreation is priced on the RecPricing sheet.
A21: STAFF RATES
A22: Type | B22: Rate £ | C22: Basis
A23: Casual | B23: 180 | C23: per person per day
A24: Summer | B24: 300 | C24: per person per week
A27: COST CLASSIFICATION (agreed with centre — item and Fixed/Variable category)
A28: Item | B28: Category
A29: office_supplies | B29: Fixed
A30: subscriptions | B30: Fixed
A31: travel_and_subsistence | B31: Variable
A32: miscellaneous_expenditure | B32: Variable
A33: accommodation | B33: Variable
A34: internal_purchases_catering | B34: Variable
A35: cleaning | B35: Variable
A36: consumables | B36: Variable
A37: laboratory_consumables | B37: Variable
A38: disposables | B38: Variable
A39: furniture | B39: Fixed
... A88: septic | B88: Fixed

Sheet RecPricing
A1: Recreation pricing (2024 tariff) — edit rates here
A2: Tiers by headcount: <=24 (Nov/Feb only), <=32 flat per course, Above 32 per head. Unknown client defaults to UoB.
A4: Client | B4: Band | C4: Max people | D4: Basis | E4: Rate £ | F4: Key
A5: UoB | B5: <=24 | C5: 24 | D5: per_course | E5: 1200 | F5: =A5&"|"&B5 -> UoB|<=24
A6: UoB | B6: <=32 | C6: 32 | D6: per_course | E6: 1680 | F6: =A6&"|"&B6 -> UoB|<=32
A7: UoB | B7: Above32 | C7: 9999 | D7: per_head | E7: 45 | F7: =A7&"|"&B7 -> UoB|Above32
A8: External | B8: <=24 | C8: 24 | D8: per_course | E8: 1225 | F8: =A8&"|"&B8 -> External|<=24
A9: External | B9: <=32 | C9: 32 | D9: per_course | E9: 2465 | F9: =A9&"|"&B9 -> External|<=32
A10: External | B10: Above32 | C10: 9999 | D10: per_head | E10: 65 | F10: =A10&"|"&B10 -> External|Above32

Sheet Bookings
A1: Course / Camp | B1: Product | C1: Client | D1: Start | E1: End | F1: People | G1: Nights | H1: Bed-nights | I1: List rate £ | J1: Invoiced £ | K1: Discount £ | L1: Income £ | M1: Deposit £ | N1: Amount Received £ | O1: Outstanding £ | P1: FY
G2: =IF(OR(D2="",E2=""),"",E2-D2) | H2: =IF(OR(F2="",G2=""),"",F2*G2) | I2: =IF(B2="Recreation",IFERROR(INDEX(RecPricing!$E$5:$E$10,MATCH(IF(C2="Mixed","External",IF(C2="Unknown","UoB",C2))&"|"&IF(F2<=24,"<=24",IF(F2<=32,"<=32","Above32")),RecPricing!$F$5:$F$10,0)),""),IFERROR(INDEX(Reference!$E$5:$E$12,MATCH(B2&"|"&IF(C2="Mixed","External",IF(C2="Unknown","UoB",C2))&"|"&IF(F2<=32,"32","40"),Reference!$D$5:$D$12,0)),"")) | J2: =IF(I2="","",IF(B2="Recreation",IF(F2<=32,I2,I2*IF(F2="",0,F2)),IF(AND(I2<>"",G2<>""),I2*G2,""))) | L2: =IF(J2="","",J2-IF(K2="",0,K2)) | O2: =IF(L2="","",L2-IF(M2="",0,M2)-IF(N2="",0,N2)) | P2: =IF(D2="","",IF(MONTH(D2)>=8,YEAR(D2)&"-"&RIGHT(YEAR(D2)+1,2),YEAR(D2)-1&"-"&RIGHT(YEAR(D2),2)))
G3: =IF(OR(D3="",E3=""),"",E3-D3) | H3: =IF(OR(F3="",G3=""),"",F3*G3) | I3: =IF(B3="Recreation",IFERROR(INDEX(RecPricing!$E$5:$E$10,MATCH(IF(C3="Mixed","External",IF(C3="Unknown","UoB",C3))&"|"&IF(F3<=24,"<=24",IF(F3<=32,"<=32","Above32")),RecPricing!$F$5:$F$10,0)),""),IFERROR(INDEX(Reference!$E$5:$E$12,MATCH(B3&"|"&IF(C3="Mixed","External",IF(C3="Unknown","UoB",C3))&"|"&IF(F3<=32,"32","40"),Reference!$D$5:$D$12,0)),"")) | J3: =IF(I3="","",IF(B3="Recreation",IF(F3<=32,I3,I3*IF(F3="",0,F3)),IF(AND(I3<>"",G3<>""),I3*G3,""))) | L3: =IF(J3="","",J3-IF(K3="",0,K3)) | O3: =IF(L3="","",L3-IF(M3="",0,M3)-IF(N3="",0,N3)) | P3: =IF(D3="","",IF(MONTH(D3)>=8,YEAR(D3)&"-"&RIGHT(YEAR(D3)+1,2),YEAR(D3)-1&"-"&RIGHT(YEAR(D3),2)))
G4: =IF(OR(D4="",E4=""),"",E4-D4) | H4: =IF(OR(F4="",G4=""),"",F4*G4) | I4: =IF(B4="Recreation",IFERROR(INDEX(RecPricing!$E$5:$E$10,MATCH(IF(C4="Mixed","External",IF(C4="Unknown","UoB",C4))&"|"&IF(F4<=24,"<=24",IF(F4<=32,"<=32","Above32")),RecPricing!$F$5:$F$10,0)),""),IFERROR(INDEX(Reference!$E$5:$E$12,MATCH(B4&"|"&IF(C4="Mixed","External",IF(C4="Unknown","UoB",C4))&"|"&IF(F4<=32,"32","40"),Reference!$D$5:$D$12,0)),"")) | J4: =IF(I4="","",IF(B4="Recreation",IF(F4<=32,I4,I4*IF(F4="",0,F4)),IF(AND(I4<>"",G4<>""),I4*G4,""))) | L4: =IF(J4="","",J4-IF(K4="",0,K4)) | O4: =IF(L4="","",L4-IF(M4="",0,M4)-IF(N4="",0,N4)) | P4: =IF(D4="","",IF(MONTH(D4)>=8,YEAR(D4)&"-"&RIGHT(YEAR(D4)+1,2),YEAR(D4)-1&"-"&RIGHT(YEAR(D4),2)))
G5: =IF(OR(D5="",E5=""),"",E5-D5) | H5: =IF(OR(F5="",G5=""),"",F5*G5) | I5: =IF(B5="Recreation",IFERROR(INDEX(RecPricing!$E$5:$E$10,MATCH(IF(C5="Mixed","External",IF(C5="Unknown","UoB",C5))&"|"&IF(F5<=24,"<=24",IF(F5<=32,"<=32","Above32")),RecPricing!$F$5:$F$10,0)),""),IFERROR(INDEX(Reference!$E$5:$E$12,MATCH(B5&"|"&IF(C5="Mixed","External",IF(C5="Unknown","UoB",C5))&"|"&IF(F5<=32,"32","40"),Reference!$D$5:$D$12,0)),"")) | J5: =IF(I5="","",IF(B5="Recreation",IF(F5<=32,I5,I5*IF(F5="",0,F5)),IF(AND(I5<>"",G5<>""),I5*G5,""))) | L5: =IF(J5="","",J5-IF(K5="",0,K5)) | O5: =IF(L5="","",L5-IF(M5="",0,M5)-IF(N5="",0,N5)) | P5: =IF(D5="","",IF(MONTH(D5)>=8,YEAR(D5)&"-"&RIGHT(YEAR(D5)+1,2),YEAR(D5)-1&"-"&RIGHT(YEAR(D5),2)))
G6: =IF(OR(D6="",E6=""),"",E6-D6) | H6: =IF(OR(F6="",G6=""),"",F6*G6) | I6: =IF(B6="Recreation",IFERROR(INDEX(RecPricing!$E$5:$E$10,MATCH(IF(C6="Mixed","External",IF(C6="Unknown","UoB",C6))&"|"&IF(F6<=24,"<=24",IF(F6<=32,"<=32","Above32")),RecPricing!$F$5:$F$10,0)),""),IFERROR(INDEX(Reference!$E$5:$E$12,MATCH(B6&"|"&IF(C6="Mixed","External",IF(C6="Unknown","UoB",C6))&"|"&IF(F6<=32,"32","40"),Reference!$D$5:$D$12,0)),"")) | J6: =IF(I6="","",IF(B6="Recreation",IF(F6<=32,I6,I6*IF(F6="",0,F6)),IF(AND(I6<>"",G6<>""),I6*G6,""))) | L6: =IF(J6="","",J6-IF(K6="",0,K6)) | O6: =IF(L6="","",L6-IF(M6="",0,M6)-IF(N6="",0,N6)) | P6: =IF(D6="","",IF(MONTH(D6)>=8,YEAR(D6)&"-"&RIGHT(YEAR(D6)+1,2),YEAR(D6)-1&"-"&RIGHT(YEAR(D6),2)))
G7: =IF(OR(D7="",E7=""),"",E7-D7) | H7: =IF(OR(F7="",G7=""),"",F7*G7) | I7: =IF(B7="Recreation",IFERROR(INDEX(RecPricing!$E$5:$E$10,MATCH(IF(C7="Mixed","External",IF(C7="Unknown","UoB",C7))&"|"&IF(F7<=24,"<=24",IF(F7<=32,"<=32","Above32")),RecPricing!$F$5:$F$10,0)),""),IFERROR(INDEX(Reference!$E$5:$E$12,MATCH(B7&"|"&IF(C7="Mixed","External",IF(C7="Unknown","UoB",C7))&"|"&IF(F7<=32,"32","40"),Reference!$D$5:$D$12,0)),"")) | J7: =IF(I7="","",IF(B7="Recreation",IF(F7<=32,I7,I7*IF(F7="",0,F7)),IF(AND(I7<>"",G7<>""),I7*G7,""))) | L7: =IF(J7="","",J7-IF(K7="",0,K7)) | O7: =IF(L7="","",L7-IF(M7="",0,M7)-IF(N7="",0,N7)) | P7: =IF(D7="","",IF(MONTH(D7)>=8,YEAR(D7)&"-"&RIGHT(YEAR(D7)+1,2),YEAR(D7)-1&"-"&RIGHT(YEAR(D7),2)))
G8: =IF(OR(D8="",E8=""),"",E8-D8) | H8: =IF(OR(F8="",G8=""),"",F8*G8) | I8: =IF(B8="Recreation",IFERROR(INDEX(RecPricing!$E$5:$E$10,MATCH(IF(C8="Mixed","External",IF(C8="Unknown","UoB",C8))&"|"&IF(F8<=24,"<=24",IF(F8<=32,"<=32","Above32")),RecPricing!$F$5:$F$10,0)),""),IFERROR(INDEX(Reference!$E$5:$E$12,MATCH(B8&"|"&IF(C8="Mixed","External",IF(C8="Unknown","UoB",C8))&"|"&IF(F8<=32,"32","40"),Reference!$D$5:$D$12,0)),"")) | J8: =IF(I8="","",IF(B8="Recreation",IF(F8<=32,I8,I8*IF(F8="",0,F8)),IF(AND(I8<>"",G8<>""),I8*G8,""))) | L8: =IF(J8="","",J8-IF(K8="",0,K8)) | O8: =IF(L8="","",L8-IF(M8="",0,M8)-IF(N8="",0,N8)) | P8: =IF(D8="","",IF(MONTH(D8)>=8,YEAR(D8)&"-"&RIGHT(YEAR(D8)+1,2),YEAR(D8)-1&"-"&RIGHT(YEAR(D8),2)))
G9: =IF(OR(D9="",E9=""),"",E9-D9) | H9: =IF(OR(F9="",G9=""),"",F9*G9) | I9: =IF(B9="Recreation",IFERROR(INDEX(RecPricing!$E$5:$E$10,MATCH(IF(C9="Mixed","External",IF(C9="Unknown","UoB",C9))&"|"&IF(F9<=24,"<=24",IF(F9<=32,"<=32","Above32")),RecPricing!$F$5:$F$10,0)),""),IFERROR(INDEX(Reference!$E$5:$E$12,MATCH(B9&"|"&IF(C9="Mixed","External",IF(C9="Unknown","UoB",C9))&"|"&IF(F9<=32,"32","40"),Reference!$D$5:$D$12,0)),"")) | J9: =IF(I9="","",IF(B9="Recreation",IF(F9<=32,I9,I9*IF(F9="",0,F9)),IF(AND(I9<>"",G9<>""),I9*G9,""))) | L9: =IF(J9="","",J9-IF(K9="",0,K9)) | O9: =IF(L9="","",L9-IF(M9="",0,M9)-IF(N9="",0,N9)) | P9: =IF(D9="","",IF(MONTH(D9)>=8,YEAR(D9)&"-"&RIGHT(YEAR(D9)+1,2),YEAR(D9)-1&"-"&RIGHT(YEAR(D9),2)))
G10: =IF(OR(D10="",E10=""),"",E10-D10) | H10: =IF(OR(F10="",G10=""),"",F10*G10) | I10: =IF(B10="Recreation",IFERROR(INDEX(RecPricing!$E$5:$E$10,MATCH(IF(C10="Mixed","External",IF(C10="Unknown","UoB",C10))&"|"&IF(F10<=24,"<=24",IF(F10<=32,"<=32","Above32")),RecPricing!$F$5:$F$10,0)),""),IFERROR(INDEX(Reference!$E$5:$E$12,MATCH(B10&"|"&IF(C10="Mixed","External",IF(C10="Unknown","UoB",C10))&"|"&IF(F10<=32,"32","40"),Reference!$D$5:$D$12,0)),"")) | J10: =IF(I10="","",IF(B10="Recreation",IF(F10<=32,I10,I10*IF(F10="",0,F10)),IF(AND(I10<>"",G10<>""),I10*G10,""))) | L10: =IF(J10="","",J10-IF(K10="",0,K10)) | O10: =IF(L10="","",L10-IF(M10="",0,M10)-IF(N10="",0,N10)) | P10: =IF(D10="","",IF(MONTH(D10)>=8,YEAR(D10)&"-"&RIGHT(YEAR(D10)+1,2),YEAR(D10)-1&"-"&RIGHT(YEAR(D10),2)))
G11: =IF(OR(D11="",E11=""),"",E11-D11) | H11: =IF(OR(F11="",G11=""),"",F11*G11) | I11: =IF(B11="Recreation",IFERROR(INDEX(RecPricing!$E$5:$E$10,MATCH(IF(C11="Mixed","External",IF(C11="Unknown","UoB",C11))&"|"&IF(F11<=24,"<=24",IF(F11<=32,"<=32","Above32")),RecPricing!$F$5:$F$10,0)),""),IFERROR(INDEX(Reference!$E$5:$E$12,MATCH(B11&"|"&IF(C11="Mixed","External",IF(C11="Unknown","UoB",C11))&"|"&IF(F11<=32,"32","40"),Reference!$D$5:$D$12,0)),"")) | J11: =IF(I11="","",IF(B11="Recreation",IF(F11<=32,I11,I11*IF(F11="",0,F11)),IF(AND(I11<>"",G11<>""),I11*G11,""))) | L11: =IF(J11="","",J11-IF(K11="",0,K11)) | O11: =IF(L11="","",L11-IF(M11="",0,M11)-IF(N11="",0,N11)) | P11: =IF(D11="","",IF(MONTH(D11)>=8,YEAR(D11)&"-"&RIGHT(YEAR(D11)+1,2),YEAR(D11)-1&"-"&RIGHT(YEAR(D11),2)))
G12: =IF(OR(D12="",E12=""),"",E12-D12) | H12: =IF(OR(F12="",G12=""),"",F12*G12) | I12: =IF(B12="Recreation",IFERROR(INDEX(RecPricing!$E$5:$E$10,MATCH(IF(C12="Mixed","External",IF(C12="Unknown","UoB",C12))&"|"&IF(F12<=24,"<=24",IF(F12<=32,"<=32","Above32")),RecPricing!$F$5:$F$10,0)),""),IFERROR(INDEX(Reference!$E$5:$E$12,MATCH(B12&"|"&IF(C12="Mixed","External",IF(C12="Unknown","UoB",C12))&"|"&IF(F12<=32,"32","40"),Reference!$D$5:$D$12,0)),"")) | J12: =IF(I12="","",IF(B12="Recreation",IF(F12<=32,I12,I12*IF(F12="",0,F12)),IF(AND(I12<>"",G12<>""),I12*G12,""))) | L12: =IF(J12="","",J12-IF(K12="",0,K12)) | O12: =IF(L12="","",L12-IF(M12="",0,M12)-IF(N12="",0,N12)) | P12: =IF(D12="","",IF(MONTH(D12)>=8,YEAR(D12)&"-"&RIGHT(YEAR(D12)+1,2),YEAR(D12)-1&"-"&RIGHT(YEAR(D12),2)))
G13: =IF(OR(D13="",E13=""),"",E13-D13) | H13: =IF(OR(F13="",G13=""),"",F13*G13) | I13: =IF(B13="Recreation",IFERROR(INDEX(RecPricing!$E$5:$E$10,MATCH(IF(C13="Mixed","External",IF(C13="Unknown","UoB",C13))&"|"&IF(F13<=24,"<=24",IF(F13<=32,"<=32","Above32")),RecPricing!$F$5:$F$10,0)),""),IFERROR(INDEX(Reference!$E$5:$E$12,MATCH(B13&"|"&IF(C13="Mixed","External",IF(C13="Unknown","UoB",C13))&"|"&IF(F13<=32,"32","40"),Reference!$D$5:$D$12,0)),"")) | J13: =IF(I13="","",IF(B13="Recreation",IF(F13<=32,I13,I13*IF(F13="",0,F13)),IF(AND(I13<>"",G13<>""),I13*G13,""))) | L13: =IF(J13="","",J13-IF(K13="",0,K13)) | O13: =IF(L13="","",L13-IF(M13="",0,M13)-IF(N13="",0,N13)) | P13: =IF(D13="","",IF(MONTH(D13)>=8,YEAR(D13)&"-"&RIGHT(YEAR(D13)+1,2),YEAR(D13)-1&"-"&RIGHT(YEAR(D13),2)))
... G1056: =IF(OR(D1056="",E1056=""),"",E1056-D1056) | H1056: =IF(OR(F1056="",G1056=""),"",F1056*G1056) | I1056: =IF(B1056="Recreation",IFERROR(INDEX(RecPricing!$E$5:$E$10,MATCH(IF(C1056="Mixed","External",IF(C1056="Unknown","UoB",C1056))&"|"&IF(F1056<=24,"<=24",IF(F1056<=32,"<=32","Above32")),RecPricing!$F$5:$F$10,0)),""),IFERROR(INDEX(Reference!$E$5:$E$12,MATCH(B1056&"|"&IF(C1056="Mixed","External",IF(C1056="Unknown","UoB",C1056))&"|"&IF(F1056<=32,"32","40"),Reference!$D$5:$D$12,0)),"")) | J1056: =IF(I1056="","",IF(B1056="Recreation",IF(F1056<=32,I1056,I1056*IF(F1056="",0,F1056)),IF(AND(I1056<>"",G1056<>""),I1056*G1056,""))) | L1056: =IF(J1056="","",J1056-IF(K1056="",0,K1056)) | O1056: =IF(L1056="","",L1056-IF(M1056="",0,M1056)-IF(N1056="",0,N1056)) | P1056: =IF(D1056="","",IF(MONTH(D1056)>=8,YEAR(D1056)&"-"&RIGHT(YEAR(D1056)+1,2),YEAR(D1056)-1&"-"&RIGHT(YEAR(D1056),2)))

Sheet StaffExtras
A1: Date | B1: Camp / Course | C1: Activity | D1: Type | E1: Units | F1: Rate £ | G1: Cost £ | H1: FY
F2: =IFERROR(INDEX(Reference!$B$23:$B$24,MATCH(D2,Reference!$A$23:$A$24,0)),"") | G2: =IF(OR(E2="",F2=""),"",E2*F2) | H2: =IF(A2="","",IF(MONTH(A2)>=8,YEAR(A2)&"-"&RIGHT(YEAR(A2)+1,2),YEAR(A2)-1&"-"&RIGHT(YEAR(A2),2)))
F3: =IFERROR(INDEX(Reference!$B$23:$B$24,MATCH(D3,Reference!$A$23:$A$24,0)),"") | G3: =IF(OR(E3="",F3=""),"",E3*F3) | H3: =IF(A3="","",IF(MONTH(A3)>=8,YEAR(A3)&"-"&RIGHT(YEAR(A3)+1,2),YEAR(A3)-1&"-"&RIGHT(YEAR(A3),2)))
F4: =IFERROR(INDEX(Reference!$B$23:$B$24,MATCH(D4,Reference!$A$23:$A$24,0)),"") | G4: =IF(OR(E4="",F4=""),"",E4*F4) | H4: =IF(A4="","",IF(MONTH(A4)>=8,YEAR(A4)&"-"&RIGHT(YEAR(A4)+1,2),YEAR(A4)-1&"-"&RIGHT(YEAR(A4),2)))
F5: =IFERROR(INDEX(Reference!$B$23:$B$24,MATCH(D5,Reference!$A$23:$A$24,0)),"") | G5: =IF(OR(E5="",F5=""),"",E5*F5) | H5: =IF(A5="","",IF(MONTH(A5)>=8,YEAR(A5)&"-"&RIGHT(YEAR(A5)+1,2),YEAR(A5)-1&"-"&RIGHT(YEAR(A5),2)))
F6: =IFERROR(INDEX(Reference!$B$23:$B$24,MATCH(D6,Reference!$A$23:$A$24,0)),"") | G6: =IF(OR(E6="",F6=""),"",E6*F6) | H6: =IF(A6="","",IF(MONTH(A6)>=8,YEAR(A6)&"-"&RIGHT(YEAR(A6)+1,2),YEAR(A6)-1&"-"&RIGHT(YEAR(A6),2)))
F7: =IFERROR(INDEX(Reference!$B$23:$B$24,MATCH(D7,Reference!$A$23:$A$24,0)),"") | G7: =IF(OR(E7="",F7=""),"",E7*F7) | H7: =IF(A7="","",IF(MONTH(A7)>=8,YEAR(A7)&"-"&RIGHT(YEAR(A7)+1,2),YEAR(A7)-1&"-"&RIGHT(YEAR(A7),2)))
F8: =IFERROR(INDEX(Reference!$B$23:$B$24,MATCH(D8,Reference!$A$23:$A$24,0)),"") | G8: =IF(OR(E8="",F8=""),"",E8*F8) | H8: =IF(A8="","",IF(MONTH(A8)>=8,YEAR(A8)&"-"&RIGHT(YEAR(A8)+1,2),YEAR(A8)-1&"-"&RIGHT(YEAR(A8),2)))
F9: =IFERROR(INDEX(Reference!$B$23:$B$24,MATCH(D9,Reference!$A$23:$A$24,0)),"") | G9: =IF(OR(E9="",F9=""),"",E9*F9) | H9: =IF(A9="","",IF(MONTH(A9)>=8,YEAR(A9)&"-"&RIGHT(YEAR(A9)+1,2),YEAR(A9)-1&"-"&RIGHT(YEAR(A9),2)))
F10: =IFERROR(INDEX(Reference!$B$23:$B$24,MATCH(D10,Reference!$A$23:$A$24,0)),"") | G10: =IF(OR(E10="",F10=""),"",E10*F10) | H10: =IF(A10="","",IF(MONTH(A10)>=8,YEAR(A10)&"-"&RIGHT(YEAR(A10)+1,2),YEAR(A10)-1&"-"&RIGHT(YEAR(A10),2)))
F11: =IFERROR(INDEX(Reference!$B$23:$B$24,MATCH(D11,Reference!$A$23:$A$24,0)),"") | G11: =IF(OR(E11="",F11=""),"",E11*F11) | H11: =IF(A11="","",IF(MONTH(A11)>=8,YEAR(A11)&"-"&RIGHT(YEAR(A11)+1,2),YEAR(A11)-1&"-"&RIGHT(YEAR(A11),2)))
F12: =IFERROR(INDEX(Reference!$B$23:$B$24,MATCH(D12,Reference!$A$23:$A$24,0)),"") | G12: =IF(OR(E12="",F12=""),"",E12*F12) | H12: =IF(A12="","",IF(MONTH(A12)>=8,YEAR(A12)&"-"&RIGHT(YEAR(A12)+1,2),YEAR(A12)-1&"-"&RIGHT(YEAR(A12),2)))
F13: =IFERROR(INDEX(Reference!$B$23:$B$24,MATCH(D13,Reference!$A$23:$A$24,0)),"") | G13: =IF(OR(E13="",F13=""),"",E13*F13) | H13: =IF(A13="","",IF(MONTH(A13)>=8,YEAR(A13)&"-"&RIGHT(YEAR(A13)+1,2),YEAR(A13)-1&"-"&RIGHT(YEAR(A13),2)))
... F1013: =IFERROR(INDEX(Reference!$B$23:$B$24,MATCH(D1013,Reference!$A$23:$A$24,0)),"") | G1013: =IF(OR(E1013="",F1013=""),"",E1013*F1013) | H1013: =IF(A1013="","",IF(MONTH(A1013)>=8,YEAR(A1013)&"-"&RIGHT(YEAR(A1013)+1,2),YEAR(A1013)-1&"-"&RIGHT(YEAR(A1013),2)))

Sheet Costs
A1: Date | B1: Item | C1: Category | D1: Amount £ | E1: FY | F1: Notes
C2: =IFERROR(INDEX(Reference!$B$29:$B$200,MATCH(B2,Reference!$A$29:$A$200,0)),"") | E2: =IF(A2="","",IF(MONTH(A2)>=8,YEAR(A2)&"-"&RIGHT(YEAR(A2)+1,2),YEAR(A2)-1&"-"&RIGHT(YEAR(A2),2)))
C3: =IFERROR(INDEX(Reference!$B$29:$B$200,MATCH(B3,Reference!$A$29:$A$200,0)),"") | E3: =IF(A3="","",IF(MONTH(A3)>=8,YEAR(A3)&"-"&RIGHT(YEAR(A3)+1,2),YEAR(A3)-1&"-"&RIGHT(YEAR(A3),2)))
C4: =IFERROR(INDEX(Reference!$B$29:$B$200,MATCH(B4,Reference!$A$29:$A$200,0)),"") | E4: =IF(A4="","",IF(MONTH(A4)>=8,YEAR(A4)&"-"&RIGHT(YEAR(A4)+1,2),YEAR(A4)-1&"-"&RIGHT(YEAR(A4),2)))
C5: =IFERROR(INDEX(Reference!$B$29:$B$200,MATCH(B5,Reference!$A$29:$A$200,0)),"") | E5: =IF(A5="","",IF(MONTH(A5)>=8,YEAR(A5)&"-"&RIGHT(YEAR(A5)+1,2),YEAR(A5)-1&"-"&RIGHT(YEAR(A5),2)))
C6: =IFERROR(INDEX(Reference!$B$29:$B$200,MATCH(B6,Reference!$A$29:$A$200,0)),"") | E6: =IF(A6="","",IF(MONTH(A6)>=8,YEAR(A6)&"-"&RIGHT(YEAR(A6)+1,2),YEAR(A6)-1&"-"&RIGHT(YEAR(A6),2)))
C7: =IFERROR(INDEX(Reference!$B$29:$B$200,MATCH(B7,Reference!$A$29:$A$200,0)),"") | E7: =IF(A7="","",IF(MONTH(A7)>=8,YEAR(A7)&"-"&RIGHT(YEAR(A7)+1,2),YEAR(A7)-1&"-"&RIGHT(YEAR(A7),2)))
C8: =IFERROR(INDEX(Reference!$B$29:$B$200,MATCH(B8,Reference!$A$29:$A$200,0)),"") | E8: =IF(A8="","",IF(MONTH(A8)>=8,YEAR(A8)&"-"&RIGHT(YEAR(A8)+1,2),YEAR(A8)-1&"-"&RIGHT(YEAR(A8),2)))
C9: =IFERROR(INDEX(Reference!$B$29:$B$200,MATCH(B9,Reference!$A$29:$A$200,0)),"") | E9: =IF(A9="","",IF(MONTH(A9)>=8,YEAR(A9)&"-"&RIGHT(YEAR(A9)+1,2),YEAR(A9)-1&"-"&RIGHT(YEAR(A9),2)))
C10: =IFERROR(INDEX(Reference!$B$29:$B$200,MATCH(B10,Reference!$A$29:$A$200,0)),"") | E10: =IF(A10="","",IF(MONTH(A10)>=8,YEAR(A10)&"-"&RIGHT(YEAR(A10)+1,2),YEAR(A10)-1&"-"&RIGHT(YEAR(A10),2)))
C11: =IFERROR(INDEX(Reference!$B$29:$B$200,MATCH(B11,Reference!$A$29:$A$200,0)),"") | E11: =IF(A11="","",IF(MONTH(A11)>=8,YEAR(A11)&"-"&RIGHT(YEAR(A11)+1,2),YEAR(A11)-1&"-"&RIGHT(YEAR(A11),2)))
C12: =IFERROR(INDEX(Reference!$B$29:$B$200,MATCH(B12,Reference!$A$29:$A$200,0)),"") | E12: =IF(A12="","",IF(MONTH(A12)>=8,YEAR(A12)&"-"&RIGHT(YEAR(A12)+1,2),YEAR(A12)-1&"-"&RIGHT(YEAR(A12),2)))
C13: =IFERROR(INDEX(Reference!$B$29:$B$200,MATCH(B13,Reference!$A$29:$A$200,0)),"") | E13: =IF(A13="","",IF(MONTH(A13)>=8,YEAR(A13)&"-"&RIGHT(YEAR(A13)+1,2),YEAR(A13)-1&"-"&RIGHT(YEAR(A13),2)))
... C1059: =IFERROR(INDEX(Reference!$B$29:$B$200,MATCH(B1059,Reference!$A$29:$A$200,0)),"") | E1059: =IF(A1059="","",IF(MONTH(A1059)>=8,YEAR(A1059)&"-"&RIGHT(YEAR(A1059)+1,2),YEAR(A1059)-1&"-"&RIGHT(YEAR(A1059),2)))

Sheet Dashboard
A1: Raymond Priestley Centre — Dashboard
A3: Financial year: | B3: 2025-26 | C3: (type e.g. 2024-25, 2025-26, 2026-27 — FY runs 1 Aug to 31 Jul)
A5: INCOME
A6: Total income | B6: =SUMIFS(Bookings!$L$2:$L$1056,Bookings!$P$2:$P$1056,$B$3) -> 0
A7: Homeport | B7: =SUMIFS(Bookings!$L$2:$L$1056,Bookings!$P$2:$P$1056,$B$3,Bookings!$B$2:$B$1056,"Homeport") -> 0
A8: Sherpa | B8: =SUMIFS(Bookings!$L$2:$L$1056,Bookings!$P$2:$P$1056,$B$3,Bookings!$B$2:$B$1056,"Sherpa") -> 0
A9: Recreation | B9: =SUMIFS(Bookings!$L$2:$L$1056,Bookings!$P$2:$P$1056,$B$3,Bookings!$B$2:$B$1056,"Recreation") -> 0
A10: Others | B10: =SUMIFS(Bookings!$L$2:$L$1056,Bookings!$P$2:$P$1056,$B$3,Bookings!$B$2:$B$1056,"Others") -> 0
A12: VOLUME
A13: Bed-nights | B13: =SUMIFS(Bookings!$H$2:$H$1056,Bookings!$P$2:$P$1056,$B$3) -> 0
A14: Bookings | B14: =COUNTIFS(Bookings!$P$2:$P$1056,$B$3) -> 0
A16: COSTS
A17: Fixed | B17: =SUMIFS(Costs!$D$2:$D$1059,Costs!$E$2:$E$1059,$B$3,Costs!$C$2:$C$1059,"Fixed") -> 0
A18: Variable | B18: =SUMIFS(Costs!$D$2:$D$1059,Costs!$E$2:$E$1059,$B$3,Costs!$C$2:$C$1059,"Variable") -> 0
A19: Total costs | B19: =B17+B18 -> 0
A21: UNIT ECONOMICS
A22: Fixed £/bed-night | B22: =IF(B13=0,"",B17/B13)
A23: Variable £/bed-night | B23: =IF(B13=0,"",B18/B13)
A24: Break-even £/bed-night | B24: =IF(B13=0,"",B19/B13)
A26: POSITION
A27: Income − Costs | B27: =B6-B19 -> 0
A28: Invoiced (income earned) | B28: =SUMIFS(Bookings!$J$2:$J$1056,Bookings!$P$2:$P$1056,$B$3)-SUMIFS(Bookings!$K$2:$K$1056,Bookings!$P$2:$P$1056,$B$3) -> 0
A29: Outstanding | B29: =SUMIFS(Bookings!$O$2:$O$1056,Bookings!$P$2:$P$1056,$B$3) -> 0
A31: RECREATION SEASON (selected FY)
A32: Recreation income | B32: =B9 -> 0
A33: Casual staff (recreation) | B33: =SUMIFS(StaffExtras!$G$2:$G$1013,StaffExtras!$H$2:$H$1013,$B$3,StaffExtras!$D$2:$D$1013,"Casual",StaffExtras!$C$2:$C$1013,"Recreation") -> 0
A34: Summer staff (recreation) | B34: =SUMIFS(StaffExtras!$G$2:$G$1013,StaffExtras!$H$2:$H$1013,$B$3,StaffExtras!$D$2:$D$1013,"Summer",StaffExtras!$C$2:$C$1013,"Recreation") -> 0
A35: Recreation contribution | B35: =B32-B33-B34 -> 0
A36: Staff extras on other activities | B36: =SUMIFS(StaffExtras!$G$2:$G$1013,StaffExtras!$H$2:$H$1013,$B$3)-B33-B34 -> 0
A38: STAFF EXTRAS — ALL ACTIVITIES (selected FY)
A39: Total casual staff | B39: =SUMIFS(StaffExtras!$G$2:$G$1013,StaffExtras!$H$2:$H$1013,$B$3,StaffExtras!$D$2:$D$1013,"Casual") -> 0
A40: Total summer staff | B40: =SUMIFS(StaffExtras!$G$2:$G$1013,StaffExtras!$H$2:$H$1013,$B$3,StaffExtras!$D$2:$D$1013,"Summer") -> 0
A41: Total staff extras | B41: =B39+B40 -> 0
A43: Homeport | B43: =SUMIFS(StaffExtras!$G$2:$G$1013,StaffExtras!$H$2:$H$1013,$B$3,StaffExtras!$C$2:$C$1013,"Homeport") -> 0
A44: Sherpa | B44: =SUMIFS(StaffExtras!$G$2:$G$1013,StaffExtras!$H$2:$H$1013,$B$3,StaffExtras!$C$2:$C$1013,"Sherpa") -> 0
A45: Recreation | B45: =SUMIFS(StaffExtras!$G$2:$G$1013,StaffExtras!$H$2:$H$1013,$B$3,StaffExtras!$C$2:$C$1013,"Recreation") -> 0
A46: Others | B46: =SUMIFS(StaffExtras!$G$2:$G$1013,StaffExtras!$H$2:$H$1013,$B$3,StaffExtras!$C$2:$C$1013,"Others") -> 0
A49: Notes: Income = Invoiced - Discount; Outstanding = Income - Deposit - Received. The Staff Extras block above covers ALL activities; the Recreation block isolates recreation only. Costs are recorded on the Costs sheet with a date that drives the FY. FY24/25 bookings are pre-filled as fully received.
